nuro/__init__.py
nuro/__main__.py
nuro/buckets.py
nuro/cli.py
nuro/config.py
nuro/debuglog.py
nuro/paths.py
nuro/pshost.py
nuro/registry.py
nuro/runner.py
nuro/usage.py
nuro/tests/test_cli.py
nuro/tests/test_registry.py
nuro-0.1.35.dist-info/METADATA
nuro-0.1.35.dist-info/WHEEL
nuro-0.1.35.dist-info/entry_points.txt
nuro-0.1.35.dist-info/top_level.txt
nuro-0.1.35.dist-info/RECORD
