Metadata-Version: 2.4
Name: nuro
Version: 0.1.35
Summary: nuro is a lightweight runner for fetching and executing PowerShell scripts from remote repositories.
Author: nuro
Requires-Python: >=3.10
